pyindexrepo/__init__.py
pyindexrepo/dispersion_formulas.py
pyindexrepo/main.py
pyindexrepo-0.1.16.dist-info/licenses/LICENSE
pyindexrepo-0.1.16.dist-info/METADATA
pyindexrepo-0.1.16.dist-info/WHEEL
pyindexrepo-0.1.16.dist-info/top_level.txt
pyindexrepo-0.1.16.dist-info/RECORD
