Metadata-Version: 2.4
Name: PyIndexRepo
Version: 0.1.16
Summary: Python interface for data on refractiveindex.info
Author-email: stuermer <stuermer@lsw.uni-heidelberg.de>
Requires-Python: >=3.10
License-File: LICENSE
Requires-Dist: matplotlib>=3.10.1
Requires-Dist: numba>=0.61.2
Requires-Dist: numpy>=2.2.4
Requires-Dist: pyyaml>=6.0.2
Requires-Dist: requests>=2.32.3
Requires-Dist: scipy>=1.15.2
Dynamic: license-file
